stock_test/__init__.py
stock_test/stock_test.py
stock_test-0.1.dist-info/METADATA
stock_test-0.1.dist-info/WHEEL
stock_test-0.1.dist-info/top_level.txt
stock_test-0.1.dist-info/RECORD
